<!--
WARNING: THIS IS AN AUTO-GENERATED FILE. CHANGES TO IT ARE LIKELY TO BE
OVERWRITTEN AND LOST. Changes to this xml configuration should be made using:
  virsh net-edit osp-public-trunk
or other application using the libvirt API.
-->

<network>
  <name>osp-public-trunk</name>
  <uuid>30ce6bc4-336b-4ddf-8f4e-39f49420ba95</uuid>
  <forward mode='bridge'/>
  <bridge name='ovs0'/>
  <vlan trunk='yes'>
    <tag id='246'/>
    <tag id='247'/>
    <tag id='248'/>
    <tag id='249'/>
  </vlan>
  <virtualport type='openvswitch'/>
</network>
